[
  {
    "timestamp":1777075200000,
    "latitude":25.0,
    "longitude":121.600006,
    "pm2_5":20.8,
    "pm10":31.3,
    "co":427.0,
    "no2":21.1,
    "o3":95.0,
    "aqi":59.0
  },
  {
    "timestamp":1777078800000,
    "latitude":25.0,
    "longitude":121.600006,
    "pm2_5":20.2,
    "pm10":30.2,
    "co":417.0,
    "no2":17.4,
    "o3":102.0,
    "aqi":60.0
  },
  {
    "timestamp":1777082400000,
    "latitude":25.0,
    "longitude":121.600006,
    "pm2_5":18.9,
    "pm10":29.1,
    "co":379.0,
    "no2":12.2,
    "o3":111.0,
    "aqi":60.0
  },
  {
    "timestamp":1777086000000,
    "latitude":25.0,
    "longitude":121.600006,
    "pm2_5":17.5,
    "pm10":27.4,
    "co":352.0,
    "no2":8.8,
    "o3":118.0,
    "aqi":60.0
  },
  {
    "timestamp":1777089600000,
    "latitude":25.0,
    "longitude":121.600006,
    "pm2_5":17.8,
    "pm10":28.1,
    "co":347.0,
    "no2":8.5,
    "o3":120.0,
    "aqi":60.0
  },
  {
    "timestamp":1777093200000,
    "latitude":25.0,
    "longitude":121.600006,
    "pm2_5":18.7,
    "pm10":29.6,
    "co":353.0,
    "no2":9.8,
    "o3":120.0,
    "aqi":59.0
  },
  {
    "timestamp":1777096800000,
    "latitude":25.0,
    "longitude":121.600006,
    "pm2_5":19.3,
    "pm10":30.6,
    "co":372.0,
    "no2":11.6,
    "o3":119.0,
    "aqi":58.0
  },
  {
    "timestamp":1777100400000,
    "latitude":25.0,
    "longitude":121.600006,
    "pm2_5":19.4,
    "pm10":31.0,
    "co":410.0,
    "no2":13.1,
    "o3":118.0,
    "aqi":56.0
  },
  {
    "timestamp":1777104000000,
    "latitude":25.0,
    "longitude":121.600006,
    "pm2_5":20.3,
    "pm10":32.4,
    "co":461.0,
    "no2":15.0,
    "o3":115.0,
    "aqi":54.0
  },
  {
    "timestamp":1777107600000,
    "latitude":25.0,
    "longitude":121.600006,
    "pm2_5":21.5,
    "pm10":35.2,
    "co":517.0,
    "no2":18.4,
    "o3":111.0,
    "aqi":53.0
  },
  {
    "timestamp":1777111200000,
    "latitude":25.0,
    "longitude":121.600006,
    "pm2_5":24.9,
    "pm10":38.2,
    "co":590.0,
    "no2":24.6,
    "o3":103.0,
    "aqi":51.0
  },
  {
    "timestamp":1777114800000,
    "latitude":25.0,
    "longitude":121.600006,
    "pm2_5":26.3,
    "pm10":40.3,
    "co":667.0,
    "no2":32.3,
    "o3":93.0,
    "aqi":49.0
  },
  {
    "timestamp":1777118400000,
    "latitude":25.0,
    "longitude":121.600006,
    "pm2_5":28.2,
    "pm10":42.4,
    "co":701.0,
    "no2":38.5,
    "o3":84.0,
    "aqi":47.0
  },
  {
    "timestamp":1777122000000,
    "latitude":25.0,
    "longitude":121.600006,
    "pm2_5":30.5,
    "pm10":44.2,
    "co":663.0,
    "no2":42.7,
    "o3":78.0,
    "aqi":47.0
  },
  {
    "timestamp":1777125600000,
    "latitude":25.0,
    "longitude":121.600006,
    "pm2_5":31.9,
    "pm10":45.3,
    "co":583.0,
    "no2":45.4,
    "o3":75.0,
    "aqi":47.0
  },
  {
    "timestamp":1777129200000,
    "latitude":25.0,
    "longitude":121.600006,
    "pm2_5":31.8,
    "pm10":45.2,
    "co":500.0,
    "no2":45.4,
    "o3":73.0,
    "aqi":48.0
  },
  {
    "timestamp":1777132800000,
    "latitude":25.0,
    "longitude":121.600006,
    "pm2_5":32.0,
    "pm10":45.9,
    "co":416.0,
    "no2":40.6,
    "o3":75.0,
    "aqi":49.0
  },
  {
    "timestamp":1777136400000,
    "latitude":25.0,
    "longitude":121.600006,
    "pm2_5":30.0,
    "pm10":43.8,
    "co":329.0,
    "no2":33.0,
    "o3":80.0,
    "aqi":50.0
  },
  {
    "timestamp":1777140000000,
    "latitude":25.0,
    "longitude":121.600006,
    "pm2_5":29.8,
    "pm10":44.7,
    "co":277.0,
    "no2":27.8,
    "o3":83.0,
    "aqi":51.0
  },
  {
    "timestamp":1777143600000,
    "latitude":25.0,
    "longitude":121.600006,
    "pm2_5":30.4,
    "pm10":46.4,
    "co":277.0,
    "no2":27.7,
    "o3":81.0,
    "aqi":52.0
  },
  {
    "timestamp":1777147200000,
    "latitude":25.0,
    "longitude":121.600006,
    "pm2_5":31.5,
    "pm10":49.2,
    "co":310.0,
    "no2":29.8,
    "o3":77.0,
    "aqi":54.0
  },
  {
    "timestamp":1777150800000,
    "latitude":25.0,
    "longitude":121.600006,
    "pm2_5":33.3,
    "pm10":52.6,
    "co":360.0,
    "no2":30.8,
    "o3":77.0,
    "aqi":56.0
  },
  {
    "timestamp":1777154400000,
    "latitude":25.0,
    "longitude":121.600006,
    "pm2_5":38.2,
    "pm10":58.9,
    "co":442.0,
    "no2":29.2,
    "o3":83.0,
    "aqi":59.0
  },
  {
    "timestamp":1777158000000,
    "latitude":25.0,
    "longitude":121.600006,
    "pm2_5":39.2,
    "pm10":59.8,
    "co":540.0,
    "no2":26.3,
    "o3":93.0,
    "aqi":60.0
  },
  {
    "timestamp":1777161600000,
    "latitude":25.0,
    "longitude":121.600006,
    "pm2_5":29.0,
    "pm10":50.6,
    "co":590.0,
    "no2":23.0,
    "o3":103.0,
    "aqi":61.0
  },
  {
    "timestamp":1777165200000,
    "latitude":25.0,
    "longitude":121.600006,
    "pm2_5":27.0,
    "pm10":49.8,
    "co":547.0,
    "no2":19.0,
    "o3":113.0,
    "aqi":61.0
  },
  {
    "timestamp":1777168800000,
    "latitude":25.0,
    "longitude":121.600006,
    "pm2_5":26.6,
    "pm10":49.6,
    "co":455.0,
    "no2":14.5,
    "o3":123.0,
    "aqi":62.0
  },
  {
    "timestamp":1777172400000,
    "latitude":25.0,
    "longitude":121.600006,
    "pm2_5":26.1,
    "pm10":48.4,
    "co":381.0,
    "no2":11.1,
    "o3":131.0,
    "aqi":62.0
  },
  {
    "timestamp":1777176000000,
    "latitude":25.0,
    "longitude":121.600006,
    "pm2_5":25.1,
    "pm10":45.8,
    "co":348.0,
    "no2":9.2,
    "o3":138.0,
    "aqi":62.0
  },
  {
    "timestamp":1777179600000,
    "latitude":25.0,
    "longitude":121.600006,
    "pm2_5":24.6,
    "pm10":44.0,
    "co":333.0,
    "no2":8.3,
    "o3":143.0,
    "aqi":62.0
  },
  {
    "timestamp":1777183200000,
    "latitude":25.0,
    "longitude":121.600006,
    "pm2_5":24.6,
    "pm10":43.5,
    "co":328.0,
    "no2":8.5,
    "o3":146.0,
    "aqi":63.0
  },
  {
    "timestamp":1777186800000,
    "latitude":25.0,
    "longitude":121.600006,
    "pm2_5":24.3,
    "pm10":42.6,
    "co":336.0,
    "no2":9.1,
    "o3":146.0,
    "aqi":63.0
  },
  {
    "timestamp":1777190400000,
    "latitude":25.0,
    "longitude":121.600006,
    "pm2_5":23.7,
    "pm10":41.7,
    "co":354.0,
    "no2":10.9,
    "o3":143.0,
    "aqi":63.0
  },
  {
    "timestamp":1777194000000,
    "latitude":25.0,
    "longitude":121.600006,
    "pm2_5":23.6,
    "pm10":40.7,
    "co":372.0,
    "no2":16.3,
    "o3":134.0,
    "aqi":63.0
  },
  {
    "timestamp":1777197600000,
    "latitude":25.0,
    "longitude":121.600006,
    "pm2_5":25.7,
    "pm10":41.2,
    "co":392.0,
    "no2":29.2,
    "o3":115.0,
    "aqi":63.0
  },
  {
    "timestamp":1777201200000,
    "latitude":25.0,
    "longitude":121.600006,
    "pm2_5":29.2,
    "pm10":43.8,
    "co":413.0,
    "no2":45.6,
    "o3":90.0,
    "aqi":63.0
  },
  {
    "timestamp":1777204800000,
    "latitude":25.0,
    "longitude":121.600006,
    "pm2_5":31.1,
    "pm10":45.6,
    "co":415.0,
    "no2":56.3,
    "o3":72.0,
    "aqi":63.0
  },
  {
    "timestamp":1777208400000,
    "latitude":25.0,
    "longitude":121.600006,
    "pm2_5":30.6,
    "pm10":45.2,
    "co":385.0,
    "no2":56.4,
    "o3":68.0,
    "aqi":63.0
  },
  {
    "timestamp":1777212000000,
    "latitude":25.0,
    "longitude":121.600006,
    "pm2_5":29.7,
    "pm10":44.0,
    "co":338.0,
    "no2":50.6,
    "o3":71.0,
    "aqi":63.0
  },
  {
    "timestamp":1777215600000,
    "latitude":25.0,
    "longitude":121.600006,
    "pm2_5":28.8,
    "pm10":42.7,
    "co":298.0,
    "no2":44.1,
    "o3":75.0,
    "aqi":63.0
  },
  {
    "timestamp":1777219200000,
    "latitude":25.0,
    "longitude":121.600006,
    "pm2_5":27.8,
    "pm10":41.7,
    "co":272.0,
    "no2":37.4,
    "o3":77.0,
    "aqi":63.0
  },
  {
    "timestamp":1777222800000,
    "latitude":25.0,
    "longitude":121.600006,
    "pm2_5":27.5,
    "pm10":41.0,
    "co":253.0,
    "no2":29.9,
    "o3":80.0,
    "aqi":63.0
  },
  {
    "timestamp":1777226400000,
    "latitude":25.0,
    "longitude":121.600006,
    "pm2_5":27.2,
    "pm10":40.4,
    "co":250.0,
    "no2":24.8,
    "o3":80.0,
    "aqi":63.0
  },
  {
    "timestamp":1777230000000,
    "latitude":25.0,
    "longitude":121.600006,
    "pm2_5":26.7,
    "pm10":39.6,
    "co":267.0,
    "no2":23.8,
    "o3":76.0,
    "aqi":63.0
  },
  {
    "timestamp":1777233600000,
    "latitude":25.0,
    "longitude":121.600006,
    "pm2_5":26.1,
    "pm10":38.6,
    "co":299.0,
    "no2":25.1,
    "o3":70.0,
    "aqi":63.0
  },
  {
    "timestamp":1777237200000,
    "latitude":25.0,
    "longitude":121.600006,
    "pm2_5":26.9,
    "pm10":39.0,
    "co":342.0,
    "no2":27.0,
    "o3":67.0,
    "aqi":63.0
  },
  {
    "timestamp":1777240800000,
    "latitude":25.0,
    "longitude":121.600006,
    "pm2_5":32.0,
    "pm10":43.7,
    "co":411.0,
    "no2":29.8,
    "o3":68.0,
    "aqi":62.0
  },
  {
    "timestamp":1777244400000,
    "latitude":25.0,
    "longitude":121.600006,
    "pm2_5":40.3,
    "pm10":51.0,
    "co":490.0,
    "no2":33.1,
    "o3":71.0,
    "aqi":62.0
  },
  {
    "timestamp":1777248000000,
    "latitude":25.0,
    "longitude":121.600006,
    "pm2_5":30.5,
    "pm10":44.7,
    "co":530.0,
    "no2":33.9,
    "o3":80.0,
    "aqi":62.0
  },
  {
    "timestamp":1777251600000,
    "latitude":25.0,
    "longitude":121.600006,
    "pm2_5":27.7,
    "pm10":44.0,
    "co":496.0,
    "no2":29.8,
    "o3":97.0,
    "aqi":62.0
  },
  {
    "timestamp":1777255200000,
    "latitude":25.0,
    "longitude":121.600006,
    "pm2_5":27.6,
    "pm10":47.6,
    "co":423.0,
    "no2":23.1,
    "o3":119.0,
    "aqi":62.0
  },
  {
    "timestamp":1777258800000,
    "latitude":25.0,
    "longitude":121.600006,
    "pm2_5":27.4,
    "pm10":51.5,
    "co":366.0,
    "no2":17.7,
    "o3":137.0,
    "aqi":62.0
  },
  {
    "timestamp":1777262400000,
    "latitude":25.0,
    "longitude":121.600006,
    "pm2_5":28.1,
    "pm10":52.7,
    "co":337.0,
    "no2":14.9,
    "o3":147.0,
    "aqi":63.0
  },
  {
    "timestamp":1777266000000,
    "latitude":25.0,
    "longitude":121.600006,
    "pm2_5":28.3,
    "pm10":52.7,
    "co":324.0,
    "no2":13.3,
    "o3":153.0,
    "aqi":64.0
  },
  {
    "timestamp":1777269600000,
    "latitude":25.0,
    "longitude":121.600006,
    "pm2_5":27.4,
    "pm10":49.7,
    "co":348.0,
    "no2":13.5,
    "o3":153.0,
    "aqi":64.0
  },
  {
    "timestamp":1777273200000,
    "latitude":25.0,
    "longitude":121.600006,
    "pm2_5":25.7,
    "pm10":45.8,
    "co":447.0,
    "no2":15.2,
    "o3":145.0,
    "aqi":63.0
  },
  {
    "timestamp":1777276800000,
    "latitude":25.0,
    "longitude":121.600006,
    "pm2_5":24.2,
    "pm10":41.8,
    "co":583.0,
    "no2":18.6,
    "o3":131.0,
    "aqi":63.0
  },
  {
    "timestamp":1777280400000,
    "latitude":25.0,
    "longitude":121.600006,
    "pm2_5":23.7,
    "pm10":39.2,
    "co":659.0,
    "no2":24.3,
    "o3":115.0,
    "aqi":63.0
  },
  {
    "timestamp":1777284000000,
    "latitude":25.0,
    "longitude":121.600006,
    "pm2_5":26.0,
    "pm10":38.3,
    "co":617.0,
    "no2":34.7,
    "o3":95.0,
    "aqi":63.0
  },
  {
    "timestamp":1777287600000,
    "latitude":25.0,
    "longitude":121.600006,
    "pm2_5":28.5,
    "pm10":39.2,
    "co":516.0,
    "no2":47.3,
    "o3":73.0,
    "aqi":63.0
  },
  {
    "timestamp":1777291200000,
    "latitude":25.0,
    "longitude":121.600006,
    "pm2_5":28.9,
    "pm10":39.3,
    "co":433.0,
    "no2":55.6,
    "o3":57.0,
    "aqi":63.0
  },
  {
    "timestamp":1777294800000,
    "latitude":25.0,
    "longitude":121.600006,
    "pm2_5":28.2,
    "pm10":38.6,
    "co":400.0,
    "no2":56.2,
    "o3":53.0,
    "aqi":63.0
  },
  {
    "timestamp":1777298400000,
    "latitude":25.0,
    "longitude":121.600006,
    "pm2_5":27.1,
    "pm10":37.1,
    "co":385.0,
    "no2":52.4,
    "o3":55.0,
    "aqi":63.0
  },
  {
    "timestamp":1777302000000,
    "latitude":25.0,
    "longitude":121.600006,
    "pm2_5":25.6,
    "pm10":35.0,
    "co":371.0,
    "no2":47.2,
    "o3":58.0,
    "aqi":62.0
  },
  {
    "timestamp":1777305600000,
    "latitude":25.0,
    "longitude":121.600006,
    "pm2_5":23.6,
    "pm10":32.2,
    "co":347.0,
    "no2":40.2,
    "o3":61.0,
    "aqi":62.0
  },
  {
    "timestamp":1777309200000,
    "latitude":25.0,
    "longitude":121.600006,
    "pm2_5":21.2,
    "pm10":29.1,
    "co":323.0,
    "no2":31.8,
    "o3":64.0,
    "aqi":62.0
  },
  {
    "timestamp":1777312800000,
    "latitude":25.0,
    "longitude":121.600006,
    "pm2_5":19.2,
    "pm10":26.3,
    "co":314.0,
    "no2":25.8,
    "o3":65.0,
    "aqi":62.0
  },
  {
    "timestamp":1777316400000,
    "latitude":25.0,
    "longitude":121.600006,
    "pm2_5":16.9,
    "pm10":22.9,
    "co":315.0,
    "no2":24.1,
    "o3":59.0,
    "aqi":62.0
  },
  {
    "timestamp":1777320000000,
    "latitude":25.0,
    "longitude":121.600006,
    "pm2_5":16.4,
    "pm10":21.7,
    "co":330.0,
    "no2":25.0,
    "o3":50.0,
    "aqi":61.0
  },
  {
    "timestamp":1777323600000,
    "latitude":25.0,
    "longitude":121.600006,
    "pm2_5":20.6,
    "pm10":26.2,
    "co":389.0,
    "no2":26.8,
    "o3":46.0,
    "aqi":61.0
  },
  {
    "timestamp":1777327200000,
    "latitude":25.0,
    "longitude":121.600006,
    "pm2_5":31.5,
    "pm10":37.6,
    "co":552.0,
    "no2":30.3,
    "o3":48.0,
    "aqi":61.0
  },
  {
    "timestamp":1777330800000,
    "latitude":25.0,
    "longitude":121.600006,
    "pm2_5":42.4,
    "pm10":48.3,
    "co":759.0,
    "no2":34.9,
    "o3":54.0,
    "aqi":61.0
  },
  {
    "timestamp":1777334400000,
    "latitude":25.0,
    "longitude":121.600006,
    "pm2_5":37.3,
    "pm10":46.3,
    "co":858.0,
    "no2":36.6,
    "o3":65.0,
    "aqi":61.0
  },
  {
    "timestamp":1777338000000,
    "latitude":25.0,
    "longitude":121.600006,
    "pm2_5":36.0,
    "pm10":46.3,
    "co":745.0,
    "no2":33.1,
    "o3":84.0,
    "aqi":61.0
  },
  {
    "timestamp":1777341600000,
    "latitude":25.0,
    "longitude":121.600006,
    "pm2_5":34.8,
    "pm10":46.4,
    "co":524.0,
    "no2":26.8,
    "o3":108.0,
    "aqi":61.0
  },
  {
    "timestamp":1777345200000,
    "latitude":25.0,
    "longitude":121.600006,
    "pm2_5":31.5,
    "pm10":42.8,
    "co":356.0,
    "no2":21.2,
    "o3":128.0,
    "aqi":62.0
  },
  {
    "timestamp":1777348800000,
    "latitude":25.0,
    "longitude":121.600006,
    "pm2_5":28.3,
    "pm10":38.3,
    "co":310.0,
    "no2":17.2,
    "o3":141.0,
    "aqi":62.0
  },
  {
    "timestamp":1777352400000,
    "latitude":25.0,
    "longitude":121.600006,
    "pm2_5":25.4,
    "pm10":34.1,
    "co":318.0,
    "no2":13.9,
    "o3":148.0,
    "aqi":63.0
  },
  {
    "timestamp":1777356000000,
    "latitude":25.0,
    "longitude":121.600006,
    "pm2_5":22.4,
    "pm10":30.2,
    "co":334.0,
    "no2":12.7,
    "o3":149.0,
    "aqi":63.0
  },
  {
    "timestamp":1777359600000,
    "latitude":25.0,
    "longitude":121.600006,
    "pm2_5":20.0,
    "pm10":27.3,
    "co":340.0,
    "no2":14.0,
    "o3":140.0,
    "aqi":62.0
  },
  {
    "timestamp":1777363200000,
    "latitude":25.0,
    "longitude":121.600006,
    "pm2_5":16.9,
    "pm10":22.8,
    "co":355.0,
    "no2":17.3,
    "o3":124.0,
    "aqi":61.0
  },
  {
    "timestamp":1777366800000,
    "latitude":25.0,
    "longitude":121.600006,
    "pm2_5":15.2,
    "pm10":20.2,
    "co":390.0,
    "no2":22.4,
    "o3":105.0,
    "aqi":61.0
  },
  {
    "timestamp":1777370400000,
    "latitude":25.0,
    "longitude":121.600006,
    "pm2_5":17.2,
    "pm10":21.9,
    "co":445.0,
    "no2":31.2,
    "o3":82.0,
    "aqi":61.0
  },
  {
    "timestamp":1777374000000,
    "latitude":25.0,
    "longitude":121.600006,
    "pm2_5":18.0,
    "pm10":21.8,
    "co":519.0,
    "no2":41.9,
    "o3":57.0,
    "aqi":61.0
  },
  {
    "timestamp":1777377600000,
    "latitude":25.0,
    "longitude":121.600006,
    "pm2_5":18.1,
    "pm10":21.0,
    "co":621.0,
    "no2":48.3,
    "o3":38.0,
    "aqi":60.0
  },
  {
    "timestamp":1777381200000,
    "latitude":25.0,
    "longitude":121.600006,
    "pm2_5":17.7,
    "pm10":20.0,
    "co":792.0,
    "no2":46.7,
    "o3":32.0,
    "aqi":59.0
  },
  {
    "timestamp":1777384800000,
    "latitude":25.0,
    "longitude":121.600006,
    "pm2_5":17.2,
    "pm10":19.0,
    "co":991.0,
    "no2":41.0,
    "o3":32.0,
    "aqi":57.0
  },
  {
    "timestamp":1777388400000,
    "latitude":25.0,
    "longitude":121.600006,
    "pm2_5":14.8,
    "pm10":16.2,
    "co":1105.0,
    "no2":36.3,
    "o3":33.0,
    "aqi":56.0
  },
  {
    "timestamp":1777392000000,
    "latitude":25.0,
    "longitude":121.600006,
    "pm2_5":13.1,
    "pm10":14.2,
    "co":1074.0,
    "no2":34.5,
    "o3":31.0,
    "aqi":54.0
  },
  {
    "timestamp":1777395600000,
    "latitude":25.0,
    "longitude":121.600006,
    "pm2_5":12.7,
    "pm10":13.7,
    "co":957.0,
    "no2":33.7,
    "o3":29.0,
    "aqi":52.0
  },
  {
    "timestamp":1777399200000,
    "latitude":25.0,
    "longitude":121.600006,
    "pm2_5":17.6,
    "pm10":18.8,
    "co":824.0,
    "no2":34.0,
    "o3":28.0,
    "aqi":51.0
  },
  {
    "timestamp":1777402800000,
    "latitude":25.0,
    "longitude":121.600006,
    "pm2_5":23.4,
    "pm10":25.6,
    "co":666.0,
    "no2":36.2,
    "o3":29.0,
    "aqi":50.0
  },
  {
    "timestamp":1777406400000,
    "latitude":25.0,
    "longitude":121.600006,
    "pm2_5":26.9,
    "pm10":29.7,
    "co":491.0,
    "no2":39.5,
    "o3":31.0,
    "aqi":51.0
  },
  {
    "timestamp":1777410000000,
    "latitude":25.0,
    "longitude":121.600006,
    "pm2_5":29.6,
    "pm10":33.4,
    "co":394.0,
    "no2":41.5,
    "o3":35.0,
    "aqi":53.0
  },
  {
    "timestamp":1777413600000,
    "latitude":25.0,
    "longitude":121.600006,
    "pm2_5":35.4,
    "pm10":39.8,
    "co":452.0,
    "no2":41.2,
    "o3":42.0,
    "aqi":55.0
  },
  {
    "timestamp":1777417200000,
    "latitude":25.0,
    "longitude":121.600006,
    "pm2_5":38.4,
    "pm10":42.5,
    "co":588.0,
    "no2":39.5,
    "o3":51.0,
    "aqi":55.0
  },
  {
    "timestamp":1777420800000,
    "latitude":25.0,
    "longitude":121.600006,
    "pm2_5":27.1,
    "pm10":32.1,
    "co":603.2,
    "no2":37.1,
    "o3":61.0,
    "aqi":55.0
  },
  {
    "timestamp":1777424400000,
    "latitude":25.0,
    "longitude":121.600006,
    "pm2_5":25.4,
    "pm10":30.4,
    "co":542.5,
    "no2":33.7,
    "o3":72.0,
    "aqi":53.0
  },
  {
    "timestamp":1777428000000,
    "latitude":25.0,
    "longitude":121.600006,
    "pm2_5":25.7,
    "pm10":30.3,
    "co":454.2,
    "no2":29.6,
    "o3":83.0,
    "aqi":51.0
  },
  {
    "timestamp":1777431600000,
    "latitude":25.0,
    "longitude":121.600006,
    "pm2_5":24.5,
    "pm10":28.6,
    "co":360.0,
    "no2":26.2,
    "o3":92.0,
    "aqi":50.0
  },
  {
    "timestamp":1777435200000,
    "latitude":25.0,
    "longitude":121.600006,
    "pm2_5":24.0,
    "pm10":27.7,
    "co":333.0,
    "no2":23.4,
    "o3":96.0,
    "aqi":48.0
  },
  {
    "timestamp":1777438800000,
    "latitude":25.0,
    "longitude":121.600006,
    "pm2_5":20.9,
    "pm10":24.1,
    "co":304.0,
    "no2":21.2,
    "o3":98.0,
    "aqi":48.0
  },
  {
    "timestamp":1777442400000,
    "latitude":25.0,
    "longitude":121.600006,
    "pm2_5":18.3,
    "pm10":21.6,
    "co":293.0,
    "no2":21.3,
    "o3":98.0,
    "aqi":47.0
  },
  {
    "timestamp":1777446000000,
    "latitude":25.0,
    "longitude":121.600006,
    "pm2_5":17.8,
    "pm10":21.1,
    "co":308.0,
    "no2":24.7,
    "o3":97.0,
    "aqi":46.0
  },
  {
    "timestamp":1777449600000,
    "latitude":25.0,
    "longitude":121.600006,
    "pm2_5":21.3,
    "pm10":24.6,
    "co":339.0,
    "no2":30.4,
    "o3":95.0,
    "aqi":46.0
  },
  {
    "timestamp":1777453200000,
    "latitude":25.0,
    "longitude":121.600006,
    "pm2_5":21.2,
    "pm10":24.9,
    "co":376.0,
    "no2":37.0,
    "o3":91.0,
    "aqi":47.0
  },
  {
    "timestamp":1777456800000,
    "latitude":25.0,
    "longitude":121.600006,
    "pm2_5":22.5,
    "pm10":27.1,
    "co":422.0,
    "no2":45.2,
    "o3":84.0,
    "aqi":48.0
  },
  {
    "timestamp":1777460400000,
    "latitude":25.0,
    "longitude":121.600006,
    "pm2_5":26.2,
    "pm10":30.5,
    "co":475.0,
    "no2":54.2,
    "o3":76.0,
    "aqi":49.0
  },
  {
    "timestamp":1777464000000,
    "latitude":25.0,
    "longitude":121.600006,
    "pm2_5":26.4,
    "pm10":30.5,
    "co":513.0,
    "no2":60.2,
    "o3":69.0,
    "aqi":50.0
  },
  {
    "timestamp":1777467600000,
    "latitude":25.0,
    "longitude":121.600006,
    "pm2_5":25.4,
    "pm10":29.2,
    "co":530.0,
    "no2":61.4,
    "o3":65.0,
    "aqi":51.0
  },
  {
    "timestamp":1777471200000,
    "latitude":25.0,
    "longitude":121.600006,
    "pm2_5":25.4,
    "pm10":29.0,
    "co":533.0,
    "no2":59.7,
    "o3":64.0,
    "aqi":53.0
  },
  {
    "timestamp":1777474800000,
    "latitude":25.0,
    "longitude":121.600006,
    "pm2_5":26.5,
    "pm10":29.9,
    "co":520.0,
    "no2":56.8,
    "o3":63.0,
    "aqi":54.0
  },
  {
    "timestamp":1777478400000,
    "latitude":25.0,
    "longitude":121.600006,
    "pm2_5":25.6,
    "pm10":28.9,
    "co":487.0,
    "no2":53.6,
    "o3":63.0,
    "aqi":56.0
  },
  {
    "timestamp":1777482000000,
    "latitude":25.0,
    "longitude":121.600006,
    "pm2_5":22.8,
    "pm10":26.0,
    "co":438.0,
    "no2":49.2,
    "o3":64.0,
    "aqi":58.0
  },
  {
    "timestamp":1777485600000,
    "latitude":25.0,
    "longitude":121.600006,
    "pm2_5":19.9,
    "pm10":23.3,
    "co":384.0,
    "no2":43.2,
    "o3":67.0,
    "aqi":60.0
  },
  {
    "timestamp":1777489200000,
    "latitude":25.0,
    "longitude":121.600006,
    "pm2_5":17.6,
    "pm10":21.3,
    "co":321.0,
    "no2":33.7,
    "o3":75.0,
    "aqi":60.0
  },
  {
    "timestamp":1777492800000,
    "latitude":25.0,
    "longitude":121.600006,
    "pm2_5":15.0,
    "pm10":18.8,
    "co":253.0,
    "no2":22.6,
    "o3":85.0,
    "aqi":59.0
  },
  {
    "timestamp":1777496400000,
    "latitude":25.0,
    "longitude":121.600006,
    "pm2_5":12.2,
    "pm10":15.9,
    "co":207.0,
    "no2":14.8,
    "o3":93.0,
    "aqi":57.0
  },
  {
    "timestamp":1777500000000,
    "latitude":25.0,
    "longitude":121.600006,
    "pm2_5":10.3,
    "pm10":14.2,
    "co":200.0,
    "no2":13.2,
    "o3":98.0,
    "aqi":54.0
  },
  {
    "timestamp":1777503600000,
    "latitude":25.0,
    "longitude":121.600006,
    "pm2_5":9.5,
    "pm10":13.2,
    "co":214.0,
    "no2":14.9,
    "o3":102.0,
    "aqi":50.0
  },
  {
    "timestamp":1777507200000,
    "latitude":25.0,
    "longitude":121.600006,
    "pm2_5":9.2,
    "pm10":12.5,
    "co":226.0,
    "no2":16.5,
    "o3":105.0,
    "aqi":45.0
  },
  {
    "timestamp":1777510800000,
    "latitude":25.0,
    "longitude":121.600006,
    "pm2_5":null,
    "pm10":null,
    "co":null,
    "no2":null,
    "o3":null,
    "aqi":42.0
  },
  {
    "timestamp":1777514400000,
    "latitude":25.0,
    "longitude":121.600006,
    "pm2_5":null,
    "pm10":null,
    "co":null,
    "no2":null,
    "o3":null,
    "aqi":null
  },
  {
    "timestamp":1777518000000,
    "latitude":25.0,
    "longitude":121.600006,
    "pm2_5":null,
    "pm10":null,
    "co":null,
    "no2":null,
    "o3":null,
    "aqi":null
  },
  {
    "timestamp":1777521600000,
    "latitude":25.0,
    "longitude":121.600006,
    "pm2_5":null,
    "pm10":null,
    "co":null,
    "no2":null,
    "o3":null,
    "aqi":null
  },
  {
    "timestamp":1777525200000,
    "latitude":25.0,
    "longitude":121.600006,
    "pm2_5":null,
    "pm10":null,
    "co":null,
    "no2":null,
    "o3":null,
    "aqi":null
  },
  {
    "timestamp":1777528800000,
    "latitude":25.0,
    "longitude":121.600006,
    "pm2_5":null,
    "pm10":null,
    "co":null,
    "no2":null,
    "o3":null,
    "aqi":null
  },
  {
    "timestamp":1777532400000,
    "latitude":25.0,
    "longitude":121.600006,
    "pm2_5":null,
    "pm10":null,
    "co":null,
    "no2":null,
    "o3":null,
    "aqi":null
  },
  {
    "timestamp":1777536000000,
    "latitude":25.0,
    "longitude":121.600006,
    "pm2_5":null,
    "pm10":null,
    "co":null,
    "no2":null,
    "o3":null,
    "aqi":null
  },
  {
    "timestamp":1777539600000,
    "latitude":25.0,
    "longitude":121.600006,
    "pm2_5":null,
    "pm10":null,
    "co":null,
    "no2":null,
    "o3":null,
    "aqi":null
  },
  {
    "timestamp":1777543200000,
    "latitude":25.0,
    "longitude":121.600006,
    "pm2_5":null,
    "pm10":null,
    "co":null,
    "no2":null,
    "o3":null,
    "aqi":null
  },
  {
    "timestamp":1777546800000,
    "latitude":25.0,
    "longitude":121.600006,
    "pm2_5":null,
    "pm10":null,
    "co":null,
    "no2":null,
    "o3":null,
    "aqi":null
  },
  {
    "timestamp":1777550400000,
    "latitude":25.0,
    "longitude":121.600006,
    "pm2_5":null,
    "pm10":null,
    "co":null,
    "no2":null,
    "o3":null,
    "aqi":null
  },
  {
    "timestamp":1777554000000,
    "latitude":25.0,
    "longitude":121.600006,
    "pm2_5":null,
    "pm10":null,
    "co":null,
    "no2":null,
    "o3":null,
    "aqi":null
  },
  {
    "timestamp":1777557600000,
    "latitude":25.0,
    "longitude":121.600006,
    "pm2_5":null,
    "pm10":null,
    "co":null,
    "no2":null,
    "o3":null,
    "aqi":null
  },
  {
    "timestamp":1777561200000,
    "latitude":25.0,
    "longitude":121.600006,
    "pm2_5":null,
    "pm10":null,
    "co":null,
    "no2":null,
    "o3":null,
    "aqi":null
  },
  {
    "timestamp":1777564800000,
    "latitude":25.0,
    "longitude":121.600006,
    "pm2_5":null,
    "pm10":null,
    "co":null,
    "no2":null,
    "o3":null,
    "aqi":null
  },
  {
    "timestamp":1777568400000,
    "latitude":25.0,
    "longitude":121.600006,
    "pm2_5":null,
    "pm10":null,
    "co":null,
    "no2":null,
    "o3":null,
    "aqi":null
  },
  {
    "timestamp":1777572000000,
    "latitude":25.0,
    "longitude":121.600006,
    "pm2_5":null,
    "pm10":null,
    "co":null,
    "no2":null,
    "o3":null,
    "aqi":null
  },
  {
    "timestamp":1777575600000,
    "latitude":25.0,
    "longitude":121.600006,
    "pm2_5":null,
    "pm10":null,
    "co":null,
    "no2":null,
    "o3":null,
    "aqi":null
  },
  {
    "timestamp":1777579200000,
    "latitude":25.0,
    "longitude":121.600006,
    "pm2_5":null,
    "pm10":null,
    "co":null,
    "no2":null,
    "o3":null,
    "aqi":null
  },
  {
    "timestamp":1777582800000,
    "latitude":25.0,
    "longitude":121.600006,
    "pm2_5":null,
    "pm10":null,
    "co":null,
    "no2":null,
    "o3":null,
    "aqi":null
  },
  {
    "timestamp":1777586400000,
    "latitude":25.0,
    "longitude":121.600006,
    "pm2_5":null,
    "pm10":null,
    "co":null,
    "no2":null,
    "o3":null,
    "aqi":null
  },
  {
    "timestamp":1777590000000,
    "latitude":25.0,
    "longitude":121.600006,
    "pm2_5":null,
    "pm10":null,
    "co":null,
    "no2":null,
    "o3":null,
    "aqi":null
  },
  {
    "timestamp":1777593600000,
    "latitude":25.0,
    "longitude":121.600006,
    "pm2_5":null,
    "pm10":null,
    "co":null,
    "no2":null,
    "o3":null,
    "aqi":null
  },
  {
    "timestamp":1777597200000,
    "latitude":25.0,
    "longitude":121.600006,
    "pm2_5":null,
    "pm10":null,
    "co":null,
    "no2":null,
    "o3":null,
    "aqi":null
  },
  {
    "timestamp":1777600800000,
    "latitude":25.0,
    "longitude":121.600006,
    "pm2_5":null,
    "pm10":null,
    "co":null,
    "no2":null,
    "o3":null,
    "aqi":null
  },
  {
    "timestamp":1777604400000,
    "latitude":25.0,
    "longitude":121.600006,
    "pm2_5":null,
    "pm10":null,
    "co":null,
    "no2":null,
    "o3":null,
    "aqi":null
  },
  {
    "timestamp":1777608000000,
    "latitude":25.0,
    "longitude":121.600006,
    "pm2_5":null,
    "pm10":null,
    "co":null,
    "no2":null,
    "o3":null,
    "aqi":null
  },
  {
    "timestamp":1777611600000,
    "latitude":25.0,
    "longitude":121.600006,
    "pm2_5":null,
    "pm10":null,
    "co":null,
    "no2":null,
    "o3":null,
    "aqi":null
  },
  {
    "timestamp":1777615200000,
    "latitude":25.0,
    "longitude":121.600006,
    "pm2_5":null,
    "pm10":null,
    "co":null,
    "no2":null,
    "o3":null,
    "aqi":null
  },
  {
    "timestamp":1777618800000,
    "latitude":25.0,
    "longitude":121.600006,
    "pm2_5":null,
    "pm10":null,
    "co":null,
    "no2":null,
    "o3":null,
    "aqi":null
  },
  {
    "timestamp":1777622400000,
    "latitude":25.0,
    "longitude":121.600006,
    "pm2_5":null,
    "pm10":null,
    "co":null,
    "no2":null,
    "o3":null,
    "aqi":null
  },
  {
    "timestamp":1777626000000,
    "latitude":25.0,
    "longitude":121.600006,
    "pm2_5":null,
    "pm10":null,
    "co":null,
    "no2":null,
    "o3":null,
    "aqi":null
  },
  {
    "timestamp":1777629600000,
    "latitude":25.0,
    "longitude":121.600006,
    "pm2_5":null,
    "pm10":null,
    "co":null,
    "no2":null,
    "o3":null,
    "aqi":null
  },
  {
    "timestamp":1777633200000,
    "latitude":25.0,
    "longitude":121.600006,
    "pm2_5":null,
    "pm10":null,
    "co":null,
    "no2":null,
    "o3":null,
    "aqi":null
  },
  {
    "timestamp":1777636800000,
    "latitude":25.0,
    "longitude":121.600006,
    "pm2_5":null,
    "pm10":null,
    "co":null,
    "no2":null,
    "o3":null,
    "aqi":null
  },
  {
    "timestamp":1777640400000,
    "latitude":25.0,
    "longitude":121.600006,
    "pm2_5":null,
    "pm10":null,
    "co":null,
    "no2":null,
    "o3":null,
    "aqi":null
  },
  {
    "timestamp":1777644000000,
    "latitude":25.0,
    "longitude":121.600006,
    "pm2_5":null,
    "pm10":null,
    "co":null,
    "no2":null,
    "o3":null,
    "aqi":null
  },
  {
    "timestamp":1777647600000,
    "latitude":25.0,
    "longitude":121.600006,
    "pm2_5":null,
    "pm10":null,
    "co":null,
    "no2":null,
    "o3":null,
    "aqi":null
  },
  {
    "timestamp":1777651200000,
    "latitude":25.0,
    "longitude":121.600006,
    "pm2_5":null,
    "pm10":null,
    "co":null,
    "no2":null,
    "o3":null,
    "aqi":null
  },
  {
    "timestamp":1777654800000,
    "latitude":25.0,
    "longitude":121.600006,
    "pm2_5":null,
    "pm10":null,
    "co":null,
    "no2":null,
    "o3":null,
    "aqi":null
  },
  {
    "timestamp":1777658400000,
    "latitude":25.0,
    "longitude":121.600006,
    "pm2_5":null,
    "pm10":null,
    "co":null,
    "no2":null,
    "o3":null,
    "aqi":null
  },
  {
    "timestamp":1777662000000,
    "latitude":25.0,
    "longitude":121.600006,
    "pm2_5":null,
    "pm10":null,
    "co":null,
    "no2":null,
    "o3":null,
    "aqi":null
  },
  {
    "timestamp":1777665600000,
    "latitude":25.0,
    "longitude":121.600006,
    "pm2_5":null,
    "pm10":null,
    "co":null,
    "no2":null,
    "o3":null,
    "aqi":null
  },
  {
    "timestamp":1777669200000,
    "latitude":25.0,
    "longitude":121.600006,
    "pm2_5":null,
    "pm10":null,
    "co":null,
    "no2":null,
    "o3":null,
    "aqi":null
  },
  {
    "timestamp":1777672800000,
    "latitude":25.0,
    "longitude":121.600006,
    "pm2_5":null,
    "pm10":null,
    "co":null,
    "no2":null,
    "o3":null,
    "aqi":null
  },
  {
    "timestamp":1777676400000,
    "latitude":25.0,
    "longitude":121.600006,
    "pm2_5":null,
    "pm10":null,
    "co":null,
    "no2":null,
    "o3":null,
    "aqi":null
  }
]