[
  {
    "timestamp":1780099200000,
    "latitude":25.0,
    "longitude":121.600006,
    "pm2_5":33.4,
    "pm10":55.6,
    "co":296.0,
    "no2":11.7,
    "o3":133.0,
    "aqi":61.0
  },
  {
    "timestamp":1780102800000,
    "latitude":25.0,
    "longitude":121.600006,
    "pm2_5":34.3,
    "pm10":56.7,
    "co":289.0,
    "no2":9.6,
    "o3":141.0,
    "aqi":62.0
  },
  {
    "timestamp":1780106400000,
    "latitude":25.0,
    "longitude":121.600006,
    "pm2_5":35.0,
    "pm10":57.3,
    "co":267.0,
    "no2":6.7,
    "o3":153.0,
    "aqi":64.0
  },
  {
    "timestamp":1780110000000,
    "latitude":25.0,
    "longitude":121.600006,
    "pm2_5":35.3,
    "pm10":57.0,
    "co":253.0,
    "no2":4.6,
    "o3":160.0,
    "aqi":65.0
  },
  {
    "timestamp":1780113600000,
    "latitude":25.0,
    "longitude":121.600006,
    "pm2_5":34.3,
    "pm10":54.8,
    "co":258.0,
    "no2":4.0,
    "o3":161.0,
    "aqi":66.0
  },
  {
    "timestamp":1780117200000,
    "latitude":25.0,
    "longitude":121.600006,
    "pm2_5":32.0,
    "pm10":51.0,
    "co":270.0,
    "no2":4.3,
    "o3":157.0,
    "aqi":65.0
  },
  {
    "timestamp":1780120800000,
    "latitude":25.0,
    "longitude":121.600006,
    "pm2_5":28.2,
    "pm10":45.3,
    "co":278.0,
    "no2":5.2,
    "o3":152.0,
    "aqi":64.0
  },
  {
    "timestamp":1780124400000,
    "latitude":25.0,
    "longitude":121.600006,
    "pm2_5":23.8,
    "pm10":39.0,
    "co":275.0,
    "no2":6.9,
    "o3":145.0,
    "aqi":63.0
  },
  {
    "timestamp":1780128000000,
    "latitude":25.0,
    "longitude":121.600006,
    "pm2_5":19.8,
    "pm10":33.4,
    "co":268.0,
    "no2":9.2,
    "o3":136.0,
    "aqi":61.0
  },
  {
    "timestamp":1780131600000,
    "latitude":25.0,
    "longitude":121.600006,
    "pm2_5":16.6,
    "pm10":27.9,
    "co":267.0,
    "no2":11.4,
    "o3":128.0,
    "aqi":60.0
  },
  {
    "timestamp":1780135200000,
    "latitude":25.0,
    "longitude":121.600006,
    "pm2_5":14.6,
    "pm10":23.9,
    "co":278.0,
    "no2":13.3,
    "o3":122.0,
    "aqi":59.0
  },
  {
    "timestamp":1780138800000,
    "latitude":25.0,
    "longitude":121.600006,
    "pm2_5":13.8,
    "pm10":21.8,
    "co":294.0,
    "no2":15.1,
    "o3":117.0,
    "aqi":58.0
  },
  {
    "timestamp":1780142400000,
    "latitude":25.0,
    "longitude":121.600006,
    "pm2_5":14.1,
    "pm10":21.4,
    "co":304.0,
    "no2":16.4,
    "o3":112.0,
    "aqi":56.0
  },
  {
    "timestamp":1780146000000,
    "latitude":25.0,
    "longitude":121.600006,
    "pm2_5":14.6,
    "pm10":21.6,
    "co":307.0,
    "no2":17.0,
    "o3":108.0,
    "aqi":54.0
  },
  {
    "timestamp":1780149600000,
    "latitude":25.0,
    "longitude":121.600006,
    "pm2_5":14.6,
    "pm10":21.5,
    "co":305.0,
    "no2":17.1,
    "o3":105.0,
    "aqi":53.0
  },
  {
    "timestamp":1780153200000,
    "latitude":25.0,
    "longitude":121.600006,
    "pm2_5":14.4,
    "pm10":21.1,
    "co":292.0,
    "no2":16.4,
    "o3":103.0,
    "aqi":51.0
  },
  {
    "timestamp":1780156800000,
    "latitude":25.0,
    "longitude":121.600006,
    "pm2_5":13.8,
    "pm10":20.3,
    "co":258.0,
    "no2":14.4,
    "o3":103.0,
    "aqi":50.0
  },
  {
    "timestamp":1780160400000,
    "latitude":25.0,
    "longitude":121.600006,
    "pm2_5":13.2,
    "pm10":19.6,
    "co":212.0,
    "no2":11.8,
    "o3":104.0,
    "aqi":49.0
  },
  {
    "timestamp":1780164000000,
    "latitude":25.0,
    "longitude":121.600006,
    "pm2_5":13.0,
    "pm10":19.3,
    "co":179.0,
    "no2":9.9,
    "o3":104.0,
    "aqi":48.0
  },
  {
    "timestamp":1780167600000,
    "latitude":25.0,
    "longitude":121.600006,
    "pm2_5":11.2,
    "pm10":16.5,
    "co":168.0,
    "no2":9.6,
    "o3":103.0,
    "aqi":47.0
  },
  {
    "timestamp":1780171200000,
    "latitude":25.0,
    "longitude":121.600006,
    "pm2_5":10.9,
    "pm10":16.2,
    "co":170.0,
    "no2":10.2,
    "o3":101.0,
    "aqi":46.0
  },
  {
    "timestamp":1780174800000,
    "latitude":25.0,
    "longitude":121.600006,
    "pm2_5":11.3,
    "pm10":16.7,
    "co":179.0,
    "no2":10.6,
    "o3":101.0,
    "aqi":45.0
  },
  {
    "timestamp":1780178400000,
    "latitude":25.0,
    "longitude":121.600006,
    "pm2_5":12.9,
    "pm10":18.5,
    "co":202.0,
    "no2":10.7,
    "o3":104.0,
    "aqi":44.0
  },
  {
    "timestamp":1780182000000,
    "latitude":25.0,
    "longitude":121.600006,
    "pm2_5":13.9,
    "pm10":20.8,
    "co":232.0,
    "no2":10.7,
    "o3":109.0,
    "aqi":46.0
  },
  {
    "timestamp":1780185600000,
    "latitude":25.0,
    "longitude":121.600006,
    "pm2_5":14.3,
    "pm10":21.3,
    "co":246.0,
    "no2":10.0,
    "o3":114.0,
    "aqi":49.0
  },
  {
    "timestamp":1780189200000,
    "latitude":25.0,
    "longitude":121.600006,
    "pm2_5":14.6,
    "pm10":21.6,
    "co":228.0,
    "no2":8.0,
    "o3":121.0,
    "aqi":54.0
  },
  {
    "timestamp":1780192800000,
    "latitude":25.0,
    "longitude":121.600006,
    "pm2_5":14.9,
    "pm10":22.0,
    "co":195.0,
    "no2":5.4,
    "o3":128.0,
    "aqi":59.0
  },
  {
    "timestamp":1780196400000,
    "latitude":25.0,
    "longitude":121.600006,
    "pm2_5":15.0,
    "pm10":22.1,
    "co":171.0,
    "no2":3.5,
    "o3":133.0,
    "aqi":61.0
  },
  {
    "timestamp":1780200000000,
    "latitude":25.0,
    "longitude":121.600006,
    "pm2_5":15.1,
    "pm10":22.3,
    "co":169.0,
    "no2":2.9,
    "o3":135.0,
    "aqi":61.0
  },
  {
    "timestamp":1780203600000,
    "latitude":25.0,
    "longitude":121.600006,
    "pm2_5":15.3,
    "pm10":22.6,
    "co":176.0,
    "no2":3.1,
    "o3":135.0,
    "aqi":61.0
  },
  {
    "timestamp":1780207200000,
    "latitude":25.0,
    "longitude":121.600006,
    "pm2_5":15.6,
    "pm10":23.4,
    "co":186.0,
    "no2":3.6,
    "o3":133.0,
    "aqi":61.0
  },
  {
    "timestamp":1780210800000,
    "latitude":25.0,
    "longitude":121.600006,
    "pm2_5":15.8,
    "pm10":24.1,
    "co":192.0,
    "no2":4.5,
    "o3":129.0,
    "aqi":59.0
  },
  {
    "timestamp":1780214400000,
    "latitude":25.0,
    "longitude":121.600006,
    "pm2_5":15.7,
    "pm10":24.4,
    "co":200.0,
    "no2":5.9,
    "o3":122.0,
    "aqi":55.0
  },
  {
    "timestamp":1780218000000,
    "latitude":25.0,
    "longitude":121.600006,
    "pm2_5":15.4,
    "pm10":24.4,
    "co":217.0,
    "no2":7.3,
    "o3":116.0,
    "aqi":51.0
  },
  {
    "timestamp":1780221600000,
    "latitude":25.0,
    "longitude":121.600006,
    "pm2_5":15.3,
    "pm10":24.8,
    "co":254.0,
    "no2":9.0,
    "o3":111.0,
    "aqi":47.0
  },
  {
    "timestamp":1780225200000,
    "latitude":25.0,
    "longitude":121.600006,
    "pm2_5":16.9,
    "pm10":26.4,
    "co":299.0,
    "no2":10.8,
    "o3":106.0,
    "aqi":44.0
  },
  {
    "timestamp":1780228800000,
    "latitude":25.0,
    "longitude":121.600006,
    "pm2_5":18.2,
    "pm10":28.2,
    "co":325.0,
    "no2":12.0,
    "o3":101.0,
    "aqi":41.0
  },
  {
    "timestamp":1780232400000,
    "latitude":25.0,
    "longitude":121.600006,
    "pm2_5":20.1,
    "pm10":31.1,
    "co":315.0,
    "no2":12.4,
    "o3":96.0,
    "aqi":38.0
  },
  {
    "timestamp":1780236000000,
    "latitude":25.0,
    "longitude":121.600006,
    "pm2_5":20.6,
    "pm10":31.7,
    "co":286.0,
    "no2":12.2,
    "o3":90.0,
    "aqi":36.0
  },
  {
    "timestamp":1780239600000,
    "latitude":25.0,
    "longitude":121.600006,
    "pm2_5":21.2,
    "pm10":32.1,
    "co":261.0,
    "no2":11.9,
    "o3":86.0,
    "aqi":34.0
  },
  {
    "timestamp":1780243200000,
    "latitude":25.0,
    "longitude":121.600006,
    "pm2_5":19.8,
    "pm10":29.3,
    "co":245.0,
    "no2":11.3,
    "o3":85.0,
    "aqi":34.0
  },
  {
    "timestamp":1780246800000,
    "latitude":25.0,
    "longitude":121.600006,
    "pm2_5":18.6,
    "pm10":27.0,
    "co":232.0,
    "no2":10.5,
    "o3":84.0,
    "aqi":34.0
  },
  {
    "timestamp":1780250400000,
    "latitude":25.0,
    "longitude":121.600006,
    "pm2_5":18.0,
    "pm10":25.7,
    "co":227.0,
    "no2":10.1,
    "o3":84.0,
    "aqi":34.0
  },
  {
    "timestamp":1780254000000,
    "latitude":25.0,
    "longitude":121.600006,
    "pm2_5":17.5,
    "pm10":24.6,
    "co":224.0,
    "no2":10.0,
    "o3":82.0,
    "aqi":33.0
  },
  {
    "timestamp":1780257600000,
    "latitude":25.0,
    "longitude":121.600006,
    "pm2_5":17.2,
    "pm10":24.2,
    "co":228.0,
    "no2":10.3,
    "o3":80.0,
    "aqi":32.0
  },
  {
    "timestamp":1780261200000,
    "latitude":25.0,
    "longitude":121.600006,
    "pm2_5":17.7,
    "pm10":24.4,
    "co":258.0,
    "no2":11.4,
    "o3":78.0,
    "aqi":33.0
  },
  {
    "timestamp":1780264800000,
    "latitude":25.0,
    "longitude":121.600006,
    "pm2_5":19.1,
    "pm10":25.6,
    "co":344.0,
    "no2":14.3,
    "o3":78.0,
    "aqi":33.0
  },
  {
    "timestamp":1780268400000,
    "latitude":25.0,
    "longitude":121.600006,
    "pm2_5":19.8,
    "pm10":26.7,
    "co":457.0,
    "no2":18.0,
    "o3":78.0,
    "aqi":34.0
  },
  {
    "timestamp":1780272000000,
    "latitude":25.0,
    "longitude":121.600006,
    "pm2_5":20.0,
    "pm10":26.8,
    "co":528.0,
    "no2":20.4,
    "o3":79.0,
    "aqi":34.0
  },
  {
    "timestamp":1780275600000,
    "latitude":25.0,
    "longitude":121.600006,
    "pm2_5":20.8,
    "pm10":26.8,
    "co":520.0,
    "no2":20.1,
    "o3":81.0,
    "aqi":35.0
  },
  {
    "timestamp":1780279200000,
    "latitude":25.0,
    "longitude":121.600006,
    "pm2_5":19.0,
    "pm10":25.3,
    "co":469.0,
    "no2":18.5,
    "o3":84.0,
    "aqi":35.0
  },
  {
    "timestamp":1780282800000,
    "latitude":25.0,
    "longitude":121.600006,
    "pm2_5":16.6,
    "pm10":22.4,
    "co":418.0,
    "no2":16.8,
    "o3":87.0,
    "aqi":36.0
  },
  {
    "timestamp":1780286400000,
    "latitude":25.0,
    "longitude":121.600006,
    "pm2_5":15.7,
    "pm10":21.5,
    "co":370.0,
    "no2":14.7,
    "o3":91.0,
    "aqi":36.0
  },
  {
    "timestamp":1780290000000,
    "latitude":25.0,
    "longitude":121.600006,
    "pm2_5":16.3,
    "pm10":22.5,
    "co":322.0,
    "no2":12.6,
    "o3":94.0,
    "aqi":38.0
  },
  {
    "timestamp":1780293600000,
    "latitude":25.0,
    "longitude":121.600006,
    "pm2_5":15.7,
    "pm10":21.7,
    "co":303.0,
    "no2":12.9,
    "o3":95.0,
    "aqi":38.0
  },
  {
    "timestamp":1780297200000,
    "latitude":25.0,
    "longitude":121.600006,
    "pm2_5":17.9,
    "pm10":24.3,
    "co":326.0,
    "no2":17.3,
    "o3":92.0,
    "aqi":37.0
  },
  {
    "timestamp":1780300800000,
    "latitude":25.0,
    "longitude":121.600006,
    "pm2_5":19.1,
    "pm10":25.6,
    "co":379.0,
    "no2":24.2,
    "o3":86.0,
    "aqi":36.0
  },
  {
    "timestamp":1780304400000,
    "latitude":25.0,
    "longitude":121.600006,
    "pm2_5":19.5,
    "pm10":25.6,
    "co":449.0,
    "no2":31.0,
    "o3":78.0,
    "aqi":36.0
  },
  {
    "timestamp":1780308000000,
    "latitude":25.0,
    "longitude":121.600006,
    "pm2_5":18.0,
    "pm10":23.5,
    "co":559.0,
    "no2":37.7,
    "o3":67.0,
    "aqi":37.0
  },
  {
    "timestamp":1780311600000,
    "latitude":25.0,
    "longitude":121.600006,
    "pm2_5":20.5,
    "pm10":25.7,
    "co":688.0,
    "no2":44.4,
    "o3":55.0,
    "aqi":37.0
  },
  {
    "timestamp":1780315200000,
    "latitude":25.0,
    "longitude":121.600006,
    "pm2_5":23.7,
    "pm10":28.9,
    "co":758.0,
    "no2":49.0,
    "o3":45.0,
    "aqi":37.0
  },
  {
    "timestamp":1780318800000,
    "latitude":25.0,
    "longitude":121.600006,
    "pm2_5":26.1,
    "pm10":31.2,
    "co":726.0,
    "no2":50.1,
    "o3":39.0,
    "aqi":38.0
  },
  {
    "timestamp":1780322400000,
    "latitude":25.0,
    "longitude":121.600006,
    "pm2_5":27.0,
    "pm10":31.9,
    "co":635.0,
    "no2":49.1,
    "o3":35.0,
    "aqi":38.0
  },
  {
    "timestamp":1780326000000,
    "latitude":25.0,
    "longitude":121.600006,
    "pm2_5":26.5,
    "pm10":31.1,
    "co":541.0,
    "no2":47.8,
    "o3":32.0,
    "aqi":39.0
  },
  {
    "timestamp":1780329600000,
    "latitude":25.0,
    "longitude":121.600006,
    "pm2_5":26.1,
    "pm10":30.5,
    "co":448.0,
    "no2":46.9,
    "o3":30.0,
    "aqi":39.0
  },
  {
    "timestamp":1780333200000,
    "latitude":25.0,
    "longitude":121.600006,
    "pm2_5":25.1,
    "pm10":29.2,
    "co":352.0,
    "no2":45.8,
    "o3":28.0,
    "aqi":40.0
  },
  {
    "timestamp":1780336800000,
    "latitude":25.0,
    "longitude":121.600006,
    "pm2_5":23.8,
    "pm10":27.8,
    "co":293.0,
    "no2":44.7,
    "o3":27.0,
    "aqi":40.0
  },
  {
    "timestamp":1780340400000,
    "latitude":25.0,
    "longitude":121.600006,
    "pm2_5":23.2,
    "pm10":27.0,
    "co":296.0,
    "no2":44.2,
    "o3":25.0,
    "aqi":41.0
  },
  {
    "timestamp":1780344000000,
    "latitude":25.0,
    "longitude":121.600006,
    "pm2_5":23.0,
    "pm10":26.9,
    "co":336.0,
    "no2":43.8,
    "o3":22.0,
    "aqi":42.0
  },
  {
    "timestamp":1780347600000,
    "latitude":25.0,
    "longitude":121.600006,
    "pm2_5":22.9,
    "pm10":26.8,
    "co":375.0,
    "no2":42.0,
    "o3":22.0,
    "aqi":43.0
  },
  {
    "timestamp":1780351200000,
    "latitude":25.0,
    "longitude":121.600006,
    "pm2_5":24.4,
    "pm10":28.2,
    "co":407.0,
    "no2":37.6,
    "o3":24.0,
    "aqi":44.0
  },
  {
    "timestamp":1780354800000,
    "latitude":25.0,
    "longitude":121.600006,
    "pm2_5":20.1,
    "pm10":24.5,
    "co":437.0,
    "no2":31.7,
    "o3":27.0,
    "aqi":45.0
  },
  {
    "timestamp":1780358400000,
    "latitude":25.0,
    "longitude":121.600006,
    "pm2_5":17.4,
    "pm10":21.4,
    "co":445.0,
    "no2":26.5,
    "o3":33.0,
    "aqi":45.0
  },
  {
    "timestamp":1780362000000,
    "latitude":25.0,
    "longitude":121.600006,
    "pm2_5":16.8,
    "pm10":21.0,
    "co":412.0,
    "no2":22.6,
    "o3":43.0,
    "aqi":45.0
  },
  {
    "timestamp":1780365600000,
    "latitude":25.0,
    "longitude":121.600006,
    "pm2_5":16.6,
    "pm10":21.2,
    "co":356.0,
    "no2":19.4,
    "o3":55.0,
    "aqi":44.0
  },
  {
    "timestamp":1780369200000,
    "latitude":25.0,
    "longitude":121.600006,
    "pm2_5":18.0,
    "pm10":23.2,
    "co":312.0,
    "no2":16.9,
    "o3":66.0,
    "aqi":44.0
  },
  {
    "timestamp":1780372800000,
    "latitude":25.0,
    "longitude":121.600006,
    "pm2_5":19.4,
    "pm10":24.7,
    "co":287.0,
    "no2":14.6,
    "o3":77.0,
    "aqi":44.0
  },
  {
    "timestamp":1780376400000,
    "latitude":25.0,
    "longitude":121.600006,
    "pm2_5":20.3,
    "pm10":25.5,
    "co":272.0,
    "no2":13.0,
    "o3":87.0,
    "aqi":45.0
  },
  {
    "timestamp":1780380000000,
    "latitude":25.0,
    "longitude":121.600006,
    "pm2_5":20.8,
    "pm10":25.6,
    "co":282.0,
    "no2":13.4,
    "o3":93.0,
    "aqi":45.0
  },
  {
    "timestamp":1780383600000,
    "latitude":25.0,
    "longitude":121.600006,
    "pm2_5":22.4,
    "pm10":27.1,
    "co":259.0,
    "no2":16.3,
    "o3":93.0,
    "aqi":46.0
  },
  {
    "timestamp":1780387200000,
    "latitude":25.0,
    "longitude":121.600006,
    "pm2_5":23.3,
    "pm10":28.0,
    "co":260.0,
    "no2":21.2,
    "o3":89.0,
    "aqi":47.0
  },
  {
    "timestamp":1780390800000,
    "latitude":25.0,
    "longitude":121.600006,
    "pm2_5":23.9,
    "pm10":28.3,
    "co":464.0,
    "no2":28.3,
    "o3":81.0,
    "aqi":47.0
  },
  {
    "timestamp":1780394400000,
    "latitude":25.0,
    "longitude":121.600006,
    "pm2_5":25.1,
    "pm10":29.5,
    "co":1151.0,
    "no2":39.7,
    "o3":68.0,
    "aqi":48.0
  },
  {
    "timestamp":1780398000000,
    "latitude":25.0,
    "longitude":121.600006,
    "pm2_5":32.6,
    "pm10":36.7,
    "co":2041.0,
    "no2":53.3,
    "o3":51.0,
    "aqi":49.0
  },
  {
    "timestamp":1780401600000,
    "latitude":25.0,
    "longitude":121.600006,
    "pm2_5":36.8,
    "pm10":40.9,
    "co":2476.0,
    "no2":63.1,
    "o3":40.0,
    "aqi":51.0
  },
  {
    "timestamp":1780405200000,
    "latitude":25.0,
    "longitude":121.600006,
    "pm2_5":39.3,
    "pm10":43.9,
    "co":1986.0,
    "no2":65.5,
    "o3":39.0,
    "aqi":54.0
  },
  {
    "timestamp":1780408800000,
    "latitude":25.0,
    "longitude":121.600006,
    "pm2_5":43.3,
    "pm10":48.1,
    "co":1041.0,
    "no2":64.1,
    "o3":43.0,
    "aqi":56.0
  },
  {
    "timestamp":1780412400000,
    "latitude":25.0,
    "longitude":121.600006,
    "pm2_5":48.4,
    "pm10":53.0,
    "co":391.0,
    "no2":63.6,
    "o3":45.0,
    "aqi":59.0
  },
  {
    "timestamp":1780416000000,
    "latitude":25.0,
    "longitude":121.600006,
    "pm2_5":52.9,
    "pm10":57.0,
    "co":412.0,
    "no2":66.5,
    "o3":42.0,
    "aqi":60.0
  },
  {
    "timestamp":1780419600000,
    "latitude":25.0,
    "longitude":121.600006,
    "pm2_5":49.2,
    "pm10":53.0,
    "co":728.0,
    "no2":70.4,
    "o3":36.0,
    "aqi":61.0
  },
  {
    "timestamp":1780423200000,
    "latitude":25.0,
    "longitude":121.600006,
    "pm2_5":44.9,
    "pm10":48.1,
    "co":956.0,
    "no2":72.9,
    "o3":31.0,
    "aqi":62.0
  },
  {
    "timestamp":1780426800000,
    "latitude":25.0,
    "longitude":121.600006,
    "pm2_5":41.8,
    "pm10":44.9,
    "co":932.0,
    "no2":73.2,
    "o3":27.0,
    "aqi":63.0
  },
  {
    "timestamp":1780430400000,
    "latitude":25.0,
    "longitude":121.600006,
    "pm2_5":40.2,
    "pm10":44.1,
    "co":820.0,
    "no2":72.2,
    "o3":23.0,
    "aqi":63.0
  },
  {
    "timestamp":1780434000000,
    "latitude":25.0,
    "longitude":121.600006,
    "pm2_5":40.9,
    "pm10":44.9,
    "co":729.0,
    "no2":69.9,
    "o3":23.0,
    "aqi":64.0
  },
  {
    "timestamp":1780437600000,
    "latitude":25.0,
    "longitude":121.600006,
    "pm2_5":45.5,
    "pm10":49.6,
    "co":700.0,
    "no2":66.4,
    "o3":28.0,
    "aqi":65.0
  },
  {
    "timestamp":1780441200000,
    "latitude":25.0,
    "longitude":121.600006,
    "pm2_5":37.8,
    "pm10":42.5,
    "co":692.0,
    "no2":61.7,
    "o3":36.0,
    "aqi":65.0
  },
  {
    "timestamp":1780444800000,
    "latitude":25.0,
    "longitude":121.600006,
    "pm2_5":34.9,
    "pm10":40.2,
    "co":640.5,
    "no2":56.0,
    "o3":50.0,
    "aqi":66.0
  },
  {
    "timestamp":1780448400000,
    "latitude":25.0,
    "longitude":121.600006,
    "pm2_5":35.2,
    "pm10":41.1,
    "co":567.5,
    "no2":48.9,
    "o3":71.0,
    "aqi":67.0
  },
  {
    "timestamp":1780452000000,
    "latitude":25.0,
    "longitude":121.600006,
    "pm2_5":35.3,
    "pm10":41.4,
    "co":487.8,
    "no2":40.9,
    "o3":97.0,
    "aqi":67.0
  },
  {
    "timestamp":1780455600000,
    "latitude":25.0,
    "longitude":121.600006,
    "pm2_5":35.9,
    "pm10":42.1,
    "co":401.0,
    "no2":33.7,
    "o3":122.0,
    "aqi":68.0
  },
  {
    "timestamp":1780459200000,
    "latitude":25.0,
    "longitude":121.600006,
    "pm2_5":38.1,
    "pm10":44.2,
    "co":387.0,
    "no2":27.0,
    "o3":148.0,
    "aqi":68.0
  },
  {
    "timestamp":1780462800000,
    "latitude":25.0,
    "longitude":121.600006,
    "pm2_5":41.8,
    "pm10":48.1,
    "co":382.0,
    "no2":21.1,
    "o3":173.0,
    "aqi":69.0
  },
  {
    "timestamp":1780466400000,
    "latitude":25.0,
    "longitude":121.600006,
    "pm2_5":44.0,
    "pm10":49.6,
    "co":388.0,
    "no2":18.7,
    "o3":191.0,
    "aqi":71.0
  },
  {
    "timestamp":1780470000000,
    "latitude":25.0,
    "longitude":121.600006,
    "pm2_5":46.6,
    "pm10":51.0,
    "co":385.0,
    "no2":19.3,
    "o3":201.0,
    "aqi":73.0
  },
  {
    "timestamp":1780473600000,
    "latitude":25.0,
    "longitude":121.600006,
    "pm2_5":47.3,
    "pm10":50.5,
    "co":393.0,
    "no2":23.3,
    "o3":203.0,
    "aqi":73.0
  },
  {
    "timestamp":1780477200000,
    "latitude":25.0,
    "longitude":121.600006,
    "pm2_5":48.2,
    "pm10":51.1,
    "co":479.0,
    "no2":35.0,
    "o3":191.0,
    "aqi":72.0
  },
  {
    "timestamp":1780480800000,
    "latitude":25.0,
    "longitude":121.600006,
    "pm2_5":51.1,
    "pm10":53.6,
    "co":720.0,
    "no2":61.7,
    "o3":153.0,
    "aqi":73.0
  },
  {
    "timestamp":1780484400000,
    "latitude":25.0,
    "longitude":121.600006,
    "pm2_5":65.7,
    "pm10":68.0,
    "co":1039.0,
    "no2":96.1,
    "o3":101.0,
    "aqi":74.0
  },
  {
    "timestamp":1780488000000,
    "latitude":25.0,
    "longitude":121.600006,
    "pm2_5":79.4,
    "pm10":82.0,
    "co":1270.0,
    "no2":119.8,
    "o3":61.0,
    "aqi":75.0
  },
  {
    "timestamp":1780491600000,
    "latitude":25.0,
    "longitude":121.600006,
    "pm2_5":74.5,
    "pm10":77.8,
    "co":1337.0,
    "no2":123.3,
    "o3":44.0,
    "aqi":76.0
  },
  {
    "timestamp":1780495200000,
    "latitude":25.0,
    "longitude":121.600006,
    "pm2_5":73.8,
    "pm10":78.9,
    "co":1317.0,
    "no2":116.1,
    "o3":38.0,
    "aqi":77.0
  },
  {
    "timestamp":1780498800000,
    "latitude":25.0,
    "longitude":121.600006,
    "pm2_5":76.6,
    "pm10":81.0,
    "co":1271.0,
    "no2":108.6,
    "o3":35.0,
    "aqi":78.0
  },
  {
    "timestamp":1780502400000,
    "latitude":25.0,
    "longitude":121.600006,
    "pm2_5":78.7,
    "pm10":82.9,
    "co":1220.0,
    "no2":104.6,
    "o3":34.0,
    "aqi":79.0
  },
  {
    "timestamp":1780506000000,
    "latitude":25.0,
    "longitude":121.600006,
    "pm2_5":72.9,
    "pm10":77.3,
    "co":1144.0,
    "no2":100.3,
    "o3":36.0,
    "aqi":80.0
  },
  {
    "timestamp":1780509600000,
    "latitude":25.0,
    "longitude":121.600006,
    "pm2_5":63.8,
    "pm10":68.2,
    "co":1047.0,
    "no2":94.5,
    "o3":37.0,
    "aqi":81.0
  },
  {
    "timestamp":1780513200000,
    "latitude":25.0,
    "longitude":121.600006,
    "pm2_5":55.2,
    "pm10":59.5,
    "co":913.0,
    "no2":85.9,
    "o3":36.0,
    "aqi":82.0
  },
  {
    "timestamp":1780516800000,
    "latitude":25.0,
    "longitude":121.600006,
    "pm2_5":48.1,
    "pm10":52.3,
    "co":759.0,
    "no2":75.9,
    "o3":34.0,
    "aqi":82.0
  },
  {
    "timestamp":1780520400000,
    "latitude":25.0,
    "longitude":121.600006,
    "pm2_5":43.4,
    "pm10":47.3,
    "co":639.0,
    "no2":66.7,
    "o3":36.0,
    "aqi":82.0
  },
  {
    "timestamp":1780524000000,
    "latitude":25.0,
    "longitude":121.600006,
    "pm2_5":43.0,
    "pm10":46.6,
    "co":577.0,
    "no2":58.8,
    "o3":45.0,
    "aqi":82.0
  },
  {
    "timestamp":1780527600000,
    "latitude":25.0,
    "longitude":121.600006,
    "pm2_5":36.7,
    "pm10":41.0,
    "co":549.0,
    "no2":51.9,
    "o3":57.0,
    "aqi":82.0
  },
  {
    "timestamp":1780531200000,
    "latitude":25.0,
    "longitude":121.600006,
    "pm2_5":33.3,
    "pm10":37.7,
    "co":533.0,
    "no2":47.1,
    "o3":66.0,
    "aqi":82.0
  },
  {
    "timestamp":1780534800000,
    "latitude":25.0,
    "longitude":121.600006,
    "pm2_5":null,
    "pm10":null,
    "co":null,
    "no2":null,
    "o3":null,
    "aqi":82.0
  },
  {
    "timestamp":1780538400000,
    "latitude":25.0,
    "longitude":121.600006,
    "pm2_5":null,
    "pm10":null,
    "co":null,
    "no2":null,
    "o3":null,
    "aqi":null
  },
  {
    "timestamp":1780542000000,
    "latitude":25.0,
    "longitude":121.600006,
    "pm2_5":null,
    "pm10":null,
    "co":null,
    "no2":null,
    "o3":null,
    "aqi":null
  },
  {
    "timestamp":1780545600000,
    "latitude":25.0,
    "longitude":121.600006,
    "pm2_5":null,
    "pm10":null,
    "co":null,
    "no2":null,
    "o3":null,
    "aqi":null
  },
  {
    "timestamp":1780549200000,
    "latitude":25.0,
    "longitude":121.600006,
    "pm2_5":null,
    "pm10":null,
    "co":null,
    "no2":null,
    "o3":null,
    "aqi":null
  },
  {
    "timestamp":1780552800000,
    "latitude":25.0,
    "longitude":121.600006,
    "pm2_5":null,
    "pm10":null,
    "co":null,
    "no2":null,
    "o3":null,
    "aqi":null
  },
  {
    "timestamp":1780556400000,
    "latitude":25.0,
    "longitude":121.600006,
    "pm2_5":null,
    "pm10":null,
    "co":null,
    "no2":null,
    "o3":null,
    "aqi":null
  },
  {
    "timestamp":1780560000000,
    "latitude":25.0,
    "longitude":121.600006,
    "pm2_5":null,
    "pm10":null,
    "co":null,
    "no2":null,
    "o3":null,
    "aqi":null
  },
  {
    "timestamp":1780563600000,
    "latitude":25.0,
    "longitude":121.600006,
    "pm2_5":null,
    "pm10":null,
    "co":null,
    "no2":null,
    "o3":null,
    "aqi":null
  },
  {
    "timestamp":1780567200000,
    "latitude":25.0,
    "longitude":121.600006,
    "pm2_5":null,
    "pm10":null,
    "co":null,
    "no2":null,
    "o3":null,
    "aqi":null
  },
  {
    "timestamp":1780570800000,
    "latitude":25.0,
    "longitude":121.600006,
    "pm2_5":null,
    "pm10":null,
    "co":null,
    "no2":null,
    "o3":null,
    "aqi":null
  },
  {
    "timestamp":1780574400000,
    "latitude":25.0,
    "longitude":121.600006,
    "pm2_5":null,
    "pm10":null,
    "co":null,
    "no2":null,
    "o3":null,
    "aqi":null
  },
  {
    "timestamp":1780578000000,
    "latitude":25.0,
    "longitude":121.600006,
    "pm2_5":null,
    "pm10":null,
    "co":null,
    "no2":null,
    "o3":null,
    "aqi":null
  },
  {
    "timestamp":1780581600000,
    "latitude":25.0,
    "longitude":121.600006,
    "pm2_5":null,
    "pm10":null,
    "co":null,
    "no2":null,
    "o3":null,
    "aqi":null
  },
  {
    "timestamp":1780585200000,
    "latitude":25.0,
    "longitude":121.600006,
    "pm2_5":null,
    "pm10":null,
    "co":null,
    "no2":null,
    "o3":null,
    "aqi":null
  },
  {
    "timestamp":1780588800000,
    "latitude":25.0,
    "longitude":121.600006,
    "pm2_5":null,
    "pm10":null,
    "co":null,
    "no2":null,
    "o3":null,
    "aqi":null
  },
  {
    "timestamp":1780592400000,
    "latitude":25.0,
    "longitude":121.600006,
    "pm2_5":null,
    "pm10":null,
    "co":null,
    "no2":null,
    "o3":null,
    "aqi":null
  },
  {
    "timestamp":1780596000000,
    "latitude":25.0,
    "longitude":121.600006,
    "pm2_5":null,
    "pm10":null,
    "co":null,
    "no2":null,
    "o3":null,
    "aqi":null
  },
  {
    "timestamp":1780599600000,
    "latitude":25.0,
    "longitude":121.600006,
    "pm2_5":null,
    "pm10":null,
    "co":null,
    "no2":null,
    "o3":null,
    "aqi":null
  },
  {
    "timestamp":1780603200000,
    "latitude":25.0,
    "longitude":121.600006,
    "pm2_5":null,
    "pm10":null,
    "co":null,
    "no2":null,
    "o3":null,
    "aqi":null
  },
  {
    "timestamp":1780606800000,
    "latitude":25.0,
    "longitude":121.600006,
    "pm2_5":null,
    "pm10":null,
    "co":null,
    "no2":null,
    "o3":null,
    "aqi":null
  },
  {
    "timestamp":1780610400000,
    "latitude":25.0,
    "longitude":121.600006,
    "pm2_5":null,
    "pm10":null,
    "co":null,
    "no2":null,
    "o3":null,
    "aqi":null
  },
  {
    "timestamp":1780614000000,
    "latitude":25.0,
    "longitude":121.600006,
    "pm2_5":null,
    "pm10":null,
    "co":null,
    "no2":null,
    "o3":null,
    "aqi":null
  },
  {
    "timestamp":1780617600000,
    "latitude":25.0,
    "longitude":121.600006,
    "pm2_5":null,
    "pm10":null,
    "co":null,
    "no2":null,
    "o3":null,
    "aqi":null
  },
  {
    "timestamp":1780621200000,
    "latitude":25.0,
    "longitude":121.600006,
    "pm2_5":null,
    "pm10":null,
    "co":null,
    "no2":null,
    "o3":null,
    "aqi":null
  },
  {
    "timestamp":1780624800000,
    "latitude":25.0,
    "longitude":121.600006,
    "pm2_5":null,
    "pm10":null,
    "co":null,
    "no2":null,
    "o3":null,
    "aqi":null
  },
  {
    "timestamp":1780628400000,
    "latitude":25.0,
    "longitude":121.600006,
    "pm2_5":null,
    "pm10":null,
    "co":null,
    "no2":null,
    "o3":null,
    "aqi":null
  },
  {
    "timestamp":1780632000000,
    "latitude":25.0,
    "longitude":121.600006,
    "pm2_5":null,
    "pm10":null,
    "co":null,
    "no2":null,
    "o3":null,
    "aqi":null
  },
  {
    "timestamp":1780635600000,
    "latitude":25.0,
    "longitude":121.600006,
    "pm2_5":null,
    "pm10":null,
    "co":null,
    "no2":null,
    "o3":null,
    "aqi":null
  },
  {
    "timestamp":1780639200000,
    "latitude":25.0,
    "longitude":121.600006,
    "pm2_5":null,
    "pm10":null,
    "co":null,
    "no2":null,
    "o3":null,
    "aqi":null
  },
  {
    "timestamp":1780642800000,
    "latitude":25.0,
    "longitude":121.600006,
    "pm2_5":null,
    "pm10":null,
    "co":null,
    "no2":null,
    "o3":null,
    "aqi":null
  },
  {
    "timestamp":1780646400000,
    "latitude":25.0,
    "longitude":121.600006,
    "pm2_5":null,
    "pm10":null,
    "co":null,
    "no2":null,
    "o3":null,
    "aqi":null
  },
  {
    "timestamp":1780650000000,
    "latitude":25.0,
    "longitude":121.600006,
    "pm2_5":null,
    "pm10":null,
    "co":null,
    "no2":null,
    "o3":null,
    "aqi":null
  },
  {
    "timestamp":1780653600000,
    "latitude":25.0,
    "longitude":121.600006,
    "pm2_5":null,
    "pm10":null,
    "co":null,
    "no2":null,
    "o3":null,
    "aqi":null
  },
  {
    "timestamp":1780657200000,
    "latitude":25.0,
    "longitude":121.600006,
    "pm2_5":null,
    "pm10":null,
    "co":null,
    "no2":null,
    "o3":null,
    "aqi":null
  },
  {
    "timestamp":1780660800000,
    "latitude":25.0,
    "longitude":121.600006,
    "pm2_5":null,
    "pm10":null,
    "co":null,
    "no2":null,
    "o3":null,
    "aqi":null
  },
  {
    "timestamp":1780664400000,
    "latitude":25.0,
    "longitude":121.600006,
    "pm2_5":null,
    "pm10":null,
    "co":null,
    "no2":null,
    "o3":null,
    "aqi":null
  },
  {
    "timestamp":1780668000000,
    "latitude":25.0,
    "longitude":121.600006,
    "pm2_5":null,
    "pm10":null,
    "co":null,
    "no2":null,
    "o3":null,
    "aqi":null
  },
  {
    "timestamp":1780671600000,
    "latitude":25.0,
    "longitude":121.600006,
    "pm2_5":null,
    "pm10":null,
    "co":null,
    "no2":null,
    "o3":null,
    "aqi":null
  },
  {
    "timestamp":1780675200000,
    "latitude":25.0,
    "longitude":121.600006,
    "pm2_5":null,
    "pm10":null,
    "co":null,
    "no2":null,
    "o3":null,
    "aqi":null
  },
  {
    "timestamp":1780678800000,
    "latitude":25.0,
    "longitude":121.600006,
    "pm2_5":null,
    "pm10":null,
    "co":null,
    "no2":null,
    "o3":null,
    "aqi":null
  },
  {
    "timestamp":1780682400000,
    "latitude":25.0,
    "longitude":121.600006,
    "pm2_5":null,
    "pm10":null,
    "co":null,
    "no2":null,
    "o3":null,
    "aqi":null
  },
  {
    "timestamp":1780686000000,
    "latitude":25.0,
    "longitude":121.600006,
    "pm2_5":null,
    "pm10":null,
    "co":null,
    "no2":null,
    "o3":null,
    "aqi":null
  },
  {
    "timestamp":1780689600000,
    "latitude":25.0,
    "longitude":121.600006,
    "pm2_5":null,
    "pm10":null,
    "co":null,
    "no2":null,
    "o3":null,
    "aqi":null
  },
  {
    "timestamp":1780693200000,
    "latitude":25.0,
    "longitude":121.600006,
    "pm2_5":null,
    "pm10":null,
    "co":null,
    "no2":null,
    "o3":null,
    "aqi":null
  },
  {
    "timestamp":1780696800000,
    "latitude":25.0,
    "longitude":121.600006,
    "pm2_5":null,
    "pm10":null,
    "co":null,
    "no2":null,
    "o3":null,
    "aqi":null
  },
  {
    "timestamp":1780700400000,
    "latitude":25.0,
    "longitude":121.600006,
    "pm2_5":null,
    "pm10":null,
    "co":null,
    "no2":null,
    "o3":null,
    "aqi":null
  }
]